bokecc_sdk/mixins.py
bokecc_sdk/live.py
bokecc_sdk/constants.py
bokecc_sdk/__init__.py
bokecc_sdk/classroom.py
bokecc_sdk/utils.py
bokecc_sdk/exceptions.py
bokecc_sdk-0.3.2.dist-info/DESCRIPTION.rst
bokecc_sdk-0.3.2.dist-info/metadata.json
bokecc_sdk-0.3.2.dist-info/METADATA
bokecc_sdk-0.3.2.dist-info/RECORD
bokecc_sdk-0.3.2.dist-info/WHEEL
bokecc_sdk-0.3.2.dist-info/top_level.txt
