Metadata-Version: 2.0
Name: bokecc-sdk
Version: 0.3.2
Summary: SDK for bokecc.
Home-page: https://github.com/duoduo369/bokecc_sdk
Author: duoduo369
Author-email: duoduo3369@gmail.com
License: MIT
Download-URL: https://github.com/duoduo369/bokecc_sdk/archive/newest.zip
Keywords: ccsdk,bokecc,bokecc sdk
Platform: UNKNOWN
Classifier: Development Status :: 4 - Beta
Classifier: Topic :: Internet
Classifier: License :: OSI Approved :: MIT License
Classifier: Intended Audience :: Developers
Classifier: Environment :: Web Environment
Classifier: Programming Language :: Python :: 2.7
Requires-Dist: requests (==2.9.1)
Requires-Dist: arrow (==0.12.1)
